packpage/__init__.py
packpage/makanoynetwork.py
network_mallware-0.0.1.dist-info/METADATA
network_mallware-0.0.1.dist-info/WHEEL
network_mallware-0.0.1.dist-info/top_level.txt
network_mallware-0.0.1.dist-info/RECORD
