Metadata-Version: 2.1
Name: network-mallware
Version: 0.0.1
Summary: A basic network password mallware
Home-page: UNKNOWN
Author: Makanoy Sadiarosy
Author-email: otikokakhidze58@gmail.com
License: UNKNOWN
Keywords: python,video,stream,video stream,camera stream,sockets
Platform: UNKNOWN
Classifier: Development Status :: 1 - Planning
Classifier: Intended Audience :: Developers
Classifier: Programming Language :: Python :: 3
Classifier: Operating System :: Unix
Classifier: Operating System :: MacOS :: MacOS X
Classifier: Operating System :: Microsoft :: Windows
